podchecker/__init__.py
podchecker/__main__.py
podchecker/exector.py
podchecker/utils/__init__.py
podchecker/utils/logger_builder.py
podchecker/utils/print_with_color.py
podchecker/utils/time_profile.py
podchecker/utils/version_comparer.py
podchecker-0.3.0.0.dist-info/METADATA
podchecker-0.3.0.0.dist-info/WHEEL
podchecker-0.3.0.0.dist-info/top_level.txt
podchecker-0.3.0.0.dist-info/RECORD
