Metadata-Version: 2.1
Name: podchecker
Version: 0.3.0.0
Summary: package podchecker
Home-page: UNKNOWN
Author: LiTing
Author-email: UNKNOWN
License: MIT
Keywords: package pod checker
Platform: UNKNOWN
Classifier: License :: OSI Approved :: MIT License
Classifier: Operating System :: OS Independent
Classifier: Programming Language :: Python :: 3
Classifier: Programming Language :: Python :: 3.6
Classifier: Programming Language :: Python :: 3.7
